[
  {
    "generated_at": "2025-08-21T12:21:42.872Z",
    "commit": "33854f1",
    "projects": [
      {
        "projectId": "DEMO-001",
        "cliente": "Demo Cliente",
        "cost_p50": 25242.52,
        "cost_p80": 27009.5,
        "timeline_days_p50": 10.4,
        "waste_pct": 0.298,
        "qc_overall_pass": false
      }
    ]
  },
  {
    "generated_at": "2025-08-21T10:17:06.611Z",
    "commit": "60543ec",
    "projects": [
      {
        "projectId": "DEMO-001",
        "cliente": "Demo Cliente",
        "cost_p50": 25242.52,
        "cost_p80": 27009.5,
        "timeline_days_p50": 10.4,
        "waste_pct": 0.298,
        "qc_overall_pass": false
      }
    ]
  },
  {
    "generated_at": "2025-08-21T12:21:43.878Z",
    "commit": "33854f1",
    "build_env": "development",
    "projects": [
      {
        "projectId": "DEMO-001",
        "cliente": "Demo Cliente",
        "cost_p50": 25242.52,
        "cost_p80": 27009.5,
        "waste_pct": 0.298,
        "timeline_days_p50": 10.4,
        "qc_overall_pass": false,
        "pieces_count": 32,
        "sheets_used": 3
      }
    ]
  },
  {
    "generated_at": "2025-08-21T17:12:55.759Z",
    "commit": "33854f1",
    "build_env": "development",
    "projects": [
      {
        "projectId": "DEMO-001",
        "cliente": "Demo Cliente",
        "cost_p50": 25242.52,
        "cost_p80": 27009.5,
        "waste_pct": 0.298,
        "timeline_days_p50": 10.4,
        "qc_overall_pass": false,
        "pieces_count": 32,
        "sheets_used": 3
      }
    ]
  }
]